LICENSE
MANIFEST.in
README.rst
setup.cfg
setup.py
versioneer.py
artellapipe/__init__.py
artellapipe/launcher/__init__.py
artellapipe/launcher/plugins/__init__.py
artellapipe/launcher/plugins/artellamanager/__init__.py
artellapipe/launcher/plugins/artellamanager/__logging__.ini
artellapipe/launcher/plugins/artellamanager/__version__.py
artellapipe/launcher/plugins/artellamanager/_version.py
artellapipe/launcher/plugins/artellamanager/artellamanager.py
artellapipe/launcher/plugins/artellamanager/loader.py
artellapipe/launcher/plugins/artellamanager/register.py
artellapipe/launcher/plugins/artellamanager/resources/icons/color/artellamanager_plugin.png
artellapipe/launcher/plugins/artellamanager/resources/icons/default/artellamanager_plugin.png
artellapipe_launcher_plugins_artellamanager.egg-info/PKG-INFO
artellapipe_launcher_plugins_artellamanager.egg-info/SOURCES.txt
artellapipe_launcher_plugins_artellamanager.egg-info/dependency_links.txt
artellapipe_launcher_plugins_artellamanager.egg-info/not-zip-safe
artellapipe_launcher_plugins_artellamanager.egg-info/requires.txt
artellapipe_launcher_plugins_artellamanager.egg-info/top_level.txt
tests/__init__.py
tests/test_general.py