Metadata-Version: 2.1
Name: artellapipe-launcher-plugins-artellamanager
Version: 0.0.12
Summary: Repository that contains source code for ArtellaManager ArtellaPipe Launcher Plugin
Home-page: UNKNOWN
Author: Tomas Poveda
Author-email: tpovedatd@gmail.com
License: MIT
Platform: UNKNOWN
Provides-Extra: dev
Provides-Extra: test
